diffractgpt/__init__.py
diffractgpt-2024.11.21.dist-info/LICENSE
diffractgpt-2024.11.21.dist-info/METADATA
diffractgpt-2024.11.21.dist-info/WHEEL
diffractgpt-2024.11.21.dist-info/entry_points.txt
diffractgpt-2024.11.21.dist-info/top_level.txt
diffractgpt-2024.11.21.dist-info/RECORD
